.gitignore
.travis.yml
CHANGELOG.md
LICENSE
README.md
setup.py
InsideMe/AnalyzeMe
InsideMe/__init__.py
InsideMe/communication.py
InsideMe/profiler.py
InsideMe.egg-info/PKG-INFO
InsideMe.egg-info/SOURCES.txt
InsideMe.egg-info/dependency_links.txt
InsideMe.egg-info/requires.txt
InsideMe.egg-info/top_level.txt
tests/proc0.png
tests/proc1.png
tests/proc2.png
tests/proc3.png
tests/summary.png
tests/test.py