Metadata-Version: 1.1
Name: InsideMe
Version: 0.2.2
Summary: Python module for monitoring memory consumption         and duration of python codes. Work for both serial codes and         parallel programming (MPI).
Home-page: https://github.com/JulienPeloton/InsideMe
Author: Julien Peloton
Author-email: j.peloton@sussex.ac.uk
License: GPL-3.0
Download-URL: https://github.com/JulienPeloton/InsideMe/archive/0.2.2.zip
Keywords: profiling,MPI,testing
Platform: UNKNOWN
Classifier: Programming Language :: Python :: 2
Classifier: Programming Language :: Python :: 2.7
